simvue_tensorflow/__init__.py
simvue_tensorflow/extras/__init__.py
simvue_tensorflow/extras/create_alerts.py
simvue_tensorflow/extras/operators.py
simvue_tensorflow/plugin.py
simvue_tensorflow-1.0.0.dist-info/LICENSE
simvue_tensorflow-1.0.0.dist-info/METADATA
simvue_tensorflow-1.0.0.dist-info/WHEEL
simvue_tensorflow-1.0.0.dist-info/RECORD
