Metadata-Version: 2.3
Name: simvue-tensorflow
Version: 1.0.0
Summary: Plugin to allow you to easily add Simvue tracking and monitoring to the training of Tensorflow ML models.
Keywords: tracking,monitoring,metrics,alerting,metrics-gathering
Author: Matt Field
Author-email: matthew.field@ukaea.uk
Requires-Python: >=3.10,<3.14
Classifier: Development Status :: 5 - Production/Stable
Classifier: Intended Audience :: Science/Research
Classifier: License :: OSI Approved :: Apache Software License
Classifier: Natural Language :: English
Classifier: Operating System :: Unix
Classifier: Operating System :: Microsoft :: Windows
Classifier: Programming Language :: Python :: 3
Classifier: Programming Language :: Python :: 3.10
Classifier: Programming Language :: Python :: 3.11
Classifier: Programming Language :: Python :: 3.12
Classifier: Programming Language :: Python :: 3.13
Classifier: Topic :: Scientific/Engineering
Classifier: Topic :: System :: Monitoring
Classifier: Topic :: Utilities
Classifier: Typing :: Typed
Requires-Dist: simvue (>=2.0.0)
Requires-Dist: tensorflow (>=2.18.0,<3.0.0)
Project-URL: Documentation, https://docs.simvue.io
Project-URL: Homepage, https://simvue.io
Project-URL: Repository, https://github.com/simvue-io/plugins-tensorflow
